{
  "version": "2",
  "projectNumber": "863190507326",
  "projectId": "regulatory-monitor-ai-agentic",
  "appId": "1:863190507326:web:15af6ebba0b5c44ff7566f",
  "realtimeDatabaseInstanceUri": "",
  "realtimeDatabaseUrl": "",
  "storageBucket": "regulatory-monitor-ai-agentic.firebasestorage.app",
  "locationId": "",
  "apiKey": "AIzaSyCr5oVTtyYnwiImKku1ARpAr6-RrYQmZbM",
  "authDomain": "regulatory-monitor-ai-agentic.firebaseapp.com",
  "messagingSenderId": "863190507326",
  "measurementId": "G-FFZEFPJPM1"
}